brickhillapi/__init__.py
brickhillapi-0.0.2.dist-info/LICENSE
brickhillapi-0.0.2.dist-info/METADATA
brickhillapi-0.0.2.dist-info/WHEEL
brickhillapi-0.0.2.dist-info/top_level.txt
brickhillapi-0.0.2.dist-info/RECORD
