Metadata-Version: 2.1
Name: brickhillapi
Version: 0.0.2
Summary: Brick Hill API wrapper.
Home-page: UNKNOWN
Author: Yek
Author-email: gwojtysiak34@gmail.com
License: UNKNOWN
Platform: UNKNOWN
Classifier: Programming Language :: Python :: 3
Classifier: License :: OSI Approved :: MIT License
Classifier: Operating System :: OS Independent
Requires-Python: >=3.6
License-File: LICENSE
